{
    "course/course": {
        "advanced_modules": [
            "survay", 
            "annotatable", 
            "word_cloud", 
            "split_test", 
            "poll", 
            "google-document"
        ], 
        "advertised_start": null, 
        "catalog_visibility": "both", 
        "course_image": "019.jpg", 
        "discussion_topics": {
            "General": {
                "id": "course"
            }
        }, 
        "display_name": "Emprendimiento y generaci\u00f3n de ideas (Edici\u00f3n 6)", 
        "end": "2020-06-06T23:59:00Z", 
        "enrollment_end": "2020-04-13T05:00:00Z", 
        "enrollment_start": "2020-03-13T05:00:00Z", 
        "graceperiod": "36000 seconds", 
        "language": "es", 
        "minimum_grade_credit": 0.8, 
        "start": "2020-04-13T05:00:00Z", 
        "tabs": [
            {
                "name": "Courseware", 
                "type": "courseware"
            }, 
            {
                "name": "Course Info", 
                "type": "course_info"
            }, 
            {
                "name": "Textbooks", 
                "type": "textbooks"
            }, 
            {
                "name": "Discussion", 
                "type": "discussion"
            }, 
            {
                "is_hidden": true, 
                "name": "Wiki", 
                "type": "wiki"
            }, 
            {
                "name": "Progress", 
                "type": "progress"
            }
        ]
    }
}